qbraid_algorithms/__init__.py
qbraid_algorithms/_version.py
qbraid_algorithms/py.typed
qbraid_algorithms/datasets/__init__.py
qbraid_algorithms/datasets/mnist.py
qbraid_algorithms/datasets/sequences.py
qbraid_algorithms/esn/__init__.py
qbraid_algorithms/esn/exceptions.py
qbraid_algorithms/esn/model.py
qbraid_algorithms/esn/reservoir.py
qbraid_algorithms/qrc/__init__.py
qbraid_algorithms/qrc/encoding.py
qbraid_algorithms/qrc/magnus_expansion.py
qbraid_algorithms/qrc/qrc_model.py
qbraid_algorithms/qrc/time_evolution.py
qbraid_algorithms-0.0.0.dist-info/LICENSE
qbraid_algorithms-0.0.0.dist-info/METADATA
qbraid_algorithms-0.0.0.dist-info/WHEEL
qbraid_algorithms-0.0.0.dist-info/top_level.txt
qbraid_algorithms-0.0.0.dist-info/RECORD
