Metadata-Version: 2.1
Name: qbraid-algorithms
Version: 0.0.0
Summary: Python package for building, simulating, and benchmarking hybrid quantum-classical algorithms.
Author: qBraid Development Team
Author-email: contact@qbraid.com
License: GNU General Public License v3.0
Project-URL: Homepage, https://github.com/qBraid/qbraid-algorithms
Project-URL: Documentation, https://docs.qbraid.com
Project-URL: Bug Tracker, https://github.com/qBraid/qbraid-algorithms/issues
Project-URL: Discord, https://discord.gg/TPBU2sa8Et
Project-URL: Launch on Lab, https://account.qbraid.com/?gitHubUrl=https://github.com/qBraid/qbraid-algorithms.git
Keywords: qbraid,quantum,algorithms,qml
Classifier: Development Status :: 2 - Pre-Alpha
Classifier: Intended Audience :: Developers
Classifier: Intended Audience :: Science/Research
Classifier: Natural Language :: English
Classifier: Programming Language :: Python
Classifier: Programming Language :: Python :: 3
Classifier: Programming Language :: Python :: 3.10
Classifier: Programming Language :: Python :: 3.11
Classifier: Programming Language :: Python :: 3.12
Classifier: Programming Language :: Python :: 3.13
Classifier: Programming Language :: Python :: 3 :: Only
Classifier: Topic :: Scientific/Engineering
Classifier: Topic :: Scientific/Engineering :: Physics
Classifier: Typing :: Typed
Classifier: Operating System :: Microsoft :: Windows
Classifier: Operating System :: POSIX
Classifier: Operating System :: Unix
Classifier: Operating System :: MacOS
Requires-Python: >=3.10
License-File: LICENSE
Requires-Dist: torch <3.0,>=2.3
Requires-Dist: numpy <2.2,>=1.17
Requires-Dist: scipy <1.15.0,>=1.13.1
Requires-Dist: bloqade <0.16,>=0.15.12
Requires-Dist: scikit-learn <1.6.0,>=1.5.0
Provides-Extra: docs
Requires-Dist: sphinx <8.2,>=7.4 ; extra == 'docs'
Requires-Dist: sphinx-autodoc-typehints <2.6,>=1.24 ; extra == 'docs'
Requires-Dist: sphinx-rtd-theme <3.0.2,>=2.0.0 ; extra == 'docs'
Requires-Dist: docutils <0.22 ; extra == 'docs'
Requires-Dist: sphinx-copybutton ; extra == 'docs'
Provides-Extra: lint
Requires-Dist: isort ; extra == 'lint'
Requires-Dist: ruff ; extra == 'lint'
Requires-Dist: qbraid-cli ; extra == 'lint'
Provides-Extra: test
Requires-Dist: pytest ; extra == 'test'
Requires-Dist: pytest-cov ; extra == 'test'
Provides-Extra: visualization
Requires-Dist: matplotlib ; extra == 'visualization'
